{
	"step-counter": {
		"dataset": [
			{
				"day": "1",
				"steps": 11362
			},
			{
				"day": "2",
				"steps": 12870
			},
			{
				"day": "3",
				"steps": 12682
			},
			{
				"day": "4",
				"steps": 8973
			},
			{
				"day": "5",
				"steps": 13670
			},
			{
				"day": "6",
				"steps": 6356
			},
			{
				"day": "7",
				"steps": 10337
			},
			{
				"day": "8",
				"steps": 11900
			},
			{
				"day": "9",
				"steps": 4676
			},
			{
				"day": "10",
				"steps": 9934
			},
			{
				"day": "11",
				"steps": 1016
			},
			{
				"day": "12",
				"steps": 9476
			},
			{
				"day": "13",
				"steps": 10385
			},
			{
				"day": "14",
				"steps": 4028
			},
			{
				"day": "15",
				"steps": 2546
			},
			{
				"day": "16",
				"steps": 12013
			},
			{
				"day": "17",
				"steps": 11207
			},
			{
				"day": "18",
				"steps": 692
			},
			{
				"day": "19",
				"steps": 596
			},
			{
				"day": "20",
				"steps": 4085
			},
			{
				"day": "21",
				"steps": 5383
			},
			{
				"day": "22",
				"steps": 5478
			},
			{
				"day": "23",
				"steps": 14538
			},
			{
				"day": "24",
				"steps": 5924
			},
			{
				"day": "25",
				"steps": 5405
			},
			{
				"day": "26",
				"steps": 5823
			},
			{
				"day": "27",
				"steps": 13404
			},
			{
				"day": "28",
				"steps": 1668
			},
			{
				"day": "29",
				"steps": 13373
			},
			{
				"day": "30",
				"steps": 13020
			}
		]
	}
}
